lolhtml.libs/libgcc_s-27e5a392.so.1
lolhtml.pyi
lolhtml/__init__.py
lolhtml/__init__.pyi
lolhtml/lolhtml.cpython-39-i386-linux-gnu.so
lolhtml/py.typed
python_lolhtml-0.1.0.dist-info/METADATA
python_lolhtml-0.1.0.dist-info/WHEEL
python_lolhtml-0.1.0.dist-info/licenses/LICENSE-BSD
python_lolhtml-0.1.0.dist-info/licenses/LICENSE-MIT
python_lolhtml-0.1.0.dist-info/RECORD
