Metadata-Version: 2.4
Name: python-lolhtml
Version: 0.1.0
Classifier: Development Status :: 3 - Alpha
Classifier: License :: OSI Approved :: MIT License
Classifier: License :: OSI Approved :: BSD License
Classifier: Operating System :: OS Independent
Classifier: Programming Language :: Rust
Classifier: Programming Language :: Python :: Implementation :: CPython
Classifier: Programming Language :: Python :: Implementation :: PyPy
Classifier: Programming Language :: Python :: 3.8
Classifier: Programming Language :: Python :: 3.9
Classifier: Programming Language :: Python :: 3.10
Classifier: Programming Language :: Python :: 3.11
Classifier: Programming Language :: Python :: 3.12
Classifier: Programming Language :: Python :: 3.13
Classifier: Programming Language :: Python :: 3.14
Classifier: Typing :: Stubs Only
License-File: LICENSE-MIT
License-File: LICENSE-BSD
Summary: Python bindings for the lol-html Rust crate
Author-email: Jayson Fong <jayson.fong@gatech.edu>
License: BSD-3-Clause
Requires-Python: >=3.8
